PythonToolkit-24.7.25.data/data/CHANGES.txt
PythonToolkit-24.7.25.data/data/LICENSE.txt
PythonToolkit-24.7.25.data/data/README.txt
ptk_lib/PTK.py
ptk_lib/PTKengine.py
ptk_lib/__init__.py
ptk_lib/app.py
ptk_lib/misc.py
ptk_lib/controls/__init__.py
ptk_lib/controls/addressed_ctrls.py
ptk_lib/controls/aui_addons.py
ptk_lib/controls/controls.py
ptk_lib/controls/dialogs.py
ptk_lib/controls/iconbutton.py
ptk_lib/controls/infoctrl.py
ptk_lib/controls/toolpanel.py
ptk_lib/controls/toolstrip.py
ptk_lib/core_tools/__init__.py
ptk_lib/core_tools/cmdhistory/__init__.py
ptk_lib/core_tools/cmdhistory/cmdhist_control.py
ptk_lib/core_tools/cmdhistory/cmdhist_icons.py
ptk_lib/core_tools/cmdhistory/cmdhist_settings.py
ptk_lib/core_tools/cmdhistory/cmdhist_tool.py
ptk_lib/core_tools/console/__init__.py
ptk_lib/core_tools/console/address_ctrl.py
ptk_lib/core_tools/console/autocomps.py
ptk_lib/core_tools/console/calltip.py
ptk_lib/core_tools/console/console_dialogs.py
ptk_lib/core_tools/console/console_frame.py
ptk_lib/core_tools/console/console_icons.py
ptk_lib/core_tools/console/console_messages.py
ptk_lib/core_tools/console/console_settings.py
ptk_lib/core_tools/console/console_tool.py
ptk_lib/core_tools/console/engine_page.py
ptk_lib/core_tools/console/script_page.py
ptk_lib/core_tools/editor/__init__.py
ptk_lib/core_tools/editor/dbg_controls.py
ptk_lib/core_tools/editor/editor_frame.py
ptk_lib/core_tools/editor/editor_icons.py
ptk_lib/core_tools/editor/editor_messages.py
ptk_lib/core_tools/editor/editor_notebook.py
ptk_lib/core_tools/editor/editor_page.py
ptk_lib/core_tools/editor/editor_settings.py
ptk_lib/core_tools/editor/editor_tool.py
ptk_lib/core_tools/editor/search_panel.py
ptk_lib/core_tools/fileio/__init__.py
ptk_lib/core_tools/fileio/fileio.py
ptk_lib/core_tools/fileio/fileio_dialogs.py
ptk_lib/core_tools/fileio/fileio_messages.py
ptk_lib/core_tools/fileio/fileio_misc.py
ptk_lib/core_tools/fileio/pickle_io.py
ptk_lib/core_tools/inspector/__init__.py
PythonToolkit-24.7.25.dist-info/LICENSE.txt
PythonToolkit-24.7.25.dist-info/METADATA
PythonToolkit-24.7.25.dist-info/WHEEL
PythonToolkit-24.7.25.dist-info/entry_points.txt
PythonToolkit-24.7.25.dist-info/top_level.txt
PythonToolkit-24.7.25.dist-info/RECORD
