Metadata-Version: 2.1
Name: PythonToolkit
Version: 24.7.25
Summary: PythonToolkit (PTK) an interactive python environment
Home-page: http://pythontoolkit.sourceforge.net
Author: Tom Charrett
Author-email: tcharrett@gmail.com
Classifier: Programming Language :: Python :: 3
Classifier: License :: OSI Approved :: GNU General Public License (GPL)
Classifier: Topic :: Scientific/Engineering
Classifier: Intended Audience :: Developers
License-File: LICENSE.txt
Requires-Dist: wxpython
Provides-Extra: opt
Requires-Dist: numpy ; extra == 'opt'
